mqpy/__init__.py
mqpy/__main__.py
mqpy/book.py
mqpy/indicator_connector.py
mqpy/logger.py
mqpy/rates.py
mqpy/template.py
mqpy/tick.py
mqpy/trade.py
mqpy/utilities.py
mqpy-0.6.11.dist-info/LICENSE
mqpy-0.6.11.dist-info/METADATA
mqpy-0.6.11.dist-info/WHEEL
mqpy-0.6.11.dist-info/entry_points.txt
mqpy-0.6.11.dist-info/top_level.txt
mqpy-0.6.11.dist-info/RECORD
