Metadata-Version: 2.1
Name: mqpy
Version: 0.6.11
Summary: I developed this library to simplify the process of creating an Expert Advisor in MQL5. While developing in MQL5 can be complex, the same task is more streamlined in Python.
Author: Joao Euko
Author-email: Joao Euko <joao@example.com>
License: MIT
Requires-Python: >=3.8
License-File: LICENSE
Provides-Extra: dev
Requires-Dist: pre-commit>=4.0.1; extra == "dev"
Requires-Dist: pylint>=3.3.3; extra == "dev"
Requires-Dist: pytest>=8.3.4; extra == "dev"
Requires-Dist: pytest-cov>=6.0.0; extra == "dev"
Provides-Extra: docs
Requires-Dist: mkdocs>=1.6.1; extra == "docs"
Requires-Dist: mkdocs-gen-files>=0.5.0; extra == "docs"
Requires-Dist: mkdocs-jupyter>=0.25.1; extra == "docs"
Requires-Dist: mkdocs-literate-nav>=0.6.2; extra == "docs"
Requires-Dist: mkdocs-material>=9.6.12; extra == "docs"
Requires-Dist: mkdocs-section-index>=0.3.10; extra == "docs"
Requires-Dist: mkdocstrings[python]>=0.29.1; extra == "docs"
